AUTHORS.rst
CONTRIBUTING.rst
HISTORY.rst
MANIFEST.in
README.rst
setup.cfg
setup.py
docs/CLI.rst
docs/Makefile
docs/authors.rst
docs/conf.py
docs/contributing.rst
docs/extensions.rst
docs/history.rst
docs/index.rst
docs/installation.rst
docs/make.bat
docs/modules.rst
docs/usage.rst
docs/_build/html/_static/ajax-loader.gif
docs/_build/html/_static/comment-bright.png
docs/_build/html/_static/comment-close.png
docs/_build/html/_static/comment.png
docs/_build/html/_static/down-pressed.png
docs/_build/html/_static/down.png
docs/_build/html/_static/file.png
docs/_build/html/_static/minus.png
docs/_build/html/_static/plus.png
docs/_build/html/_static/up-pressed.png
docs/_build/html/_static/up.png
requirements/base.txt
requirements/docs.txt
requirements/test.txt
test_ml.egg-info/PKG-INFO
test_ml.egg-info/SOURCES.txt
test_ml.egg-info/dependency_links.txt
test_ml.egg-info/entry_points.txt
test_ml.egg-info/not-zip-safe
test_ml.egg-info/requires.txt
test_ml.egg-info/top_level.txt
testml/__init__.py
testml/conf.py
testml/constants.py
testml/controller.py
testml/exceptions.py
testml/loader.py
testml/main.py
testml/manager.py
testml/metrics.py
testml/runner.py
testml/types.py
testml/utils.py