Metadata-Version: 2.1
Name: test-ml
Version: 0.1.0
Summary: Opinionated scaffolding library for machine learning projects
Home-page: https://github.com/carlomazzaferro/test-ml
Author: Carlo Mazzaferro
Author-email: carlo.mazzaferro@u.group
License: GNU General Public License v3
Keywords: testing
Platform: UNKNOWN
Classifier: Development Status :: 2 - Pre-Alpha
Classifier: Intended Audience :: Developers
Classifier: License :: OSI Approved :: GNU General Public License v3 (GPLv3)
Classifier: Natural Language :: English
Classifier: Programming Language :: Python :: 3.6
Classifier: Programming Language :: Python :: 3.7
Provides-Extra: tf_gpu
Provides-Extra: tf
Provides-Extra: sklearn
Provides-Extra: xgboost
